mcp_dome/__init__.py
mcp_dome-0.1.0.dist-info/WHEEL
mcp_dome-0.1.0.dist-info/entry_points.txt
mcp_dome-0.1.0.dist-info/METADATA
mcp_dome-0.1.0.dist-info/RECORD
