Metadata-Version: 2.3
Name: mcp-dome
Version: 0.1.0
Summary: Add your description here
Requires-Dist: map[cli]>=1.3.0
Requires-Python: >=3.10
